get_settings_yaml/__init__.py
get_settings_yaml/parser.py
get_settings_yaml-1.0.0.dist-info/LICENSE
get_settings_yaml-1.0.0.dist-info/METADATA
get_settings_yaml-1.0.0.dist-info/WHEEL
get_settings_yaml-1.0.0.dist-info/top_level.txt
get_settings_yaml-1.0.0.dist-info/RECORD
