Metadata-Version: 2.1
Name: get-settings-yaml
Version: 1.0.0
Summary: Find and load settings.yaml data into your project
Author-email: Szymon Moliński <simon@dataverselabs.com>
Maintainer: Szymon Moliński
Keywords: settings,yaml
Classifier: Development Status :: 5 - Production/Stable
Classifier: Programming Language :: Python :: 3.8
Classifier: Programming Language :: Python :: 3.9
Classifier: Programming Language :: Python :: 3.10
Classifier: Programming Language :: Python :: 3.11
Classifier: License :: OSI Approved :: MIT License
Classifier: Operating System :: OS Independent
Classifier: Intended Audience :: Developers
Classifier: Topic :: Software Development
Classifier: Topic :: Utilities
License-File: LICENSE
Requires-Dist: pyyaml ==6.0.1
